[{"orderBy": 68, "leaderName": "何驰", "calcScore": "False", "companySize": "15-50人", "deliverCount": 0, "countAdjusted": "False", "flowScore": 173, "workYear": "1-3年", "education": "学历不限", "financeStage": "初创型(不需要融资)", "pvScore": 7.01748515556381, "city": "广州", "companyLogo": "image1/M00/00/19/CgYXBlTUWFSAfwYKAABVPZmQgqQ393.png", "createTimeSort": 1453946497000, "companyId": 13023, "industryField": "移动互联网 · 数据服务", "createTime": "2016-01-28 10:01:37", "score": 1296, "imstate": "disabled", "relScore": 980, "formatCreateTime": "10:01发布", "showOrder": 1433323169144, "salary": "8k-16k", "positionName": "Ruby开发工程师", "companyName": "艾道", "jobNature": "全职", "positonTypesMap": "None", "totalCount": 0, "positionFirstType": "技术", "adWord": 0, "positionId": 481477, "randomScore": 0, "companyShortName": "广州艾道信息咨询有限公司", "showCount": 75, "haveDeliver": "False", "hrScore": 76, "plus": "否", "positionType": "后端开发", "searchScore": 0.0, "positionAdvantage": "SAAS项目，白金五星办公，期权激励", "adjustScore": 0}, {"orderBy": 62, "leaderName": "暂没有填写", "calcScore": "False", "companySize": "50-150人", "deliverCount": 0, "countAdjusted": "False", "flowScore": 94, "workYear": "3-5年", "education": "大专", "financeStage": "初创型(天使轮)", "pvScore": 11.590903218959276, "city": "广州", "companyLogo": "image2/M00/06/99/CgpzWlX6d5GAZfonAACfPGXldQk994.jpg", "createTimeSort": 1453861194000, "companyId": 96435, "industryField": "金融 · 数据服务", "createTime": "2016-01-27 10:19:54", "score": 1239, "imstate": "disabled", "relScore": 1000, "formatCreateTime": "1天前发布", "showOrder": 0, "salary": "12k-20k", "positionName": "Ruby", "companyName": "数库科技", "jobNature": "全职", "positonTypesMap": "None", "totalCount": 0, "positionFirstType": "技术", "adWord": 0, "positionId": 1173187, "randomScore": 0, "companyShortName": "广东数库互联网金融信息服务有限公司", "showCount": 123, "haveDeliver": "False", "hrScore": 83, "plus": "否", "positionType": "后端开发", "searchScore": 0.0, "positionAdvantage": "五险一金，年轻团队", "adjustScore": 0}, {"orderBy": 24, "leaderName": "暂没有填写", "calcScore": "False", "companySize": "15-50人", "deliverCount": 0, "countAdjusted": "False", "flowScore": 98, "workYear": "不限", "education": "学历不限", "financeStage": "初创型(未融资)", "pvScore": 11.368307163311346, "city": "广州", "companyLogo": "image2/M00/02/E3/CgqLKVXs2GSALnCHAAAcd5_TgNI705.png", "createTimeSort": 1452658924000, "companyId": 62288, "industryField": "移动互联网 · 企业服务", "createTime": "2016-01-13 12:22:04", "score": 1155, "imstate": "disabled", "relScore": 980, "formatCreateTime": "2016-01-13", "showOrder": 0, "salary": "6k-8k", "positionName": "Ruby开发", "companyName": "Beansmile", "jobNature": "全职", "positonTypesMap": "None", "totalCount": 0, "positionFirstType": "技术", "adWord": 0, "positionId": 1197957, "randomScore": 0, "companyShortName": "广州乐豆信息科技有限公司", "showCount": 40, "haveDeliver": "False", "hrScore": 53, "plus": "否", "positionType": "后端开发", "searchScore": 0.0, "positionAdvantage": "专业团队，前沿技术，开放氛围，热爱分享", "adjustScore": 0}, {"orderBy": 68, "leaderName": "何驰", "calcScore": "False", "companySize": "15-50人", "deliverCount": 0, "countAdjusted": "False", "flowScore": 198, "workYear": "不限", "education": "学历不限", "financeStage": "初创型(不需要融资)", "pvScore": 5.520420545043394, "city": "广州", "companyLogo": "image1/M00/00/19/CgYXBlTUWFSAfwYKAABVPZmQgqQ393.png", "createTimeSort": 1453946495000, "companyId": 13023, "industryField": "移动互联网 · 数据服务", "createTime": "2016-01-28 10:01:35", "score": 1106, "imstate": "disabled", "relScore": 765, "formatCreateTime": "10:01发布", "showOrder": 1433323160859, "salary": "3k-5k", "positionName": "Ruby开发实习生", "companyName": "艾道", "jobNature": "实习", "positonTypesMap": "None", "totalCount": 0, "positionFirstType": "技术", "adWord": 0, "positionId": 542591, "randomScore": 0, "companyShortName": "广州艾道信息咨询有限公司", "showCount": 59, "haveDeliver": "False", "hrScore": 76, "plus": "否", "positionType": "后端开发", "searchScore": 0.0, "positionAdvantage": "移动互联网，SAAS，期权激励，实习全职皆可", "adjustScore": 0}, {"orderBy": 35, "leaderName": "暂没有填写", "calcScore": "False", "companySize": "150-500人", "deliverCount": 0, "countAdjusted": "False", "flowScore": 67, "workYear": "1-3年", "education": "本科", "financeStage": "成长型(B轮)", "pvScore": 13.211600072111061, "city": "广州", "companyLogo": "image1/M00/22/47/Cgo8PFVAgjqAXyT1AABcbz3dMwQ234.jpg", "createTimeSort": 1453456711000, "companyId": 26677, "industryField": "电子商务 · 社交网络", "createTime": "2016-01-22 17:58:31", "score": 1096, "imstate": "disabled", "relScore": 931, "formatCreateTime": "2016-01-22", "showOrder": 0, "salary": "9k-15k", "positionName": "Ruby（服务端开发工程师）", "companyName": "米莱珠宝", "jobNature": "全职", "positonTypesMap": "None", "totalCount": 0, "positionFirstType": "技术", "adWord": 0, "positionId": 1225009, "randomScore": 0, "companyShortName": "米莱珠宝", "showCount": 73, "haveDeliver": "False", "hrScore": 64, "plus": "否", "positionType": "后端开发", "searchScore": 0.0, "positionAdvantage": "福利待遇好，发展前程大", "adjustScore": 0}, {"orderBy": 41, "leaderName": "梅文珏", "calcScore": "False", "companySize": "500-2000人", "deliverCount": 0, "countAdjusted": "False", "flowScore": 43, "workYear": "1-3年", "education": "本科", "financeStage": "成长型(B轮)", "pvScore": 14.607255676392684, "city": "广州", "companyLogo": "image1/M00/00/17/Cgo8PFTUWEmAPUFPAABjO4a2Xe4675.jpg", "createTimeSort": 1453428653000, "companyId": 11489, "industryField": "生活服务", "createTime": "2016-01-22 10:10:53", "score": 1096, "imstate": "disabled", "relScore": 980, "formatCreateTime": "2016-01-22", "showOrder": 0, "salary": "8k-15k", "positionName": "Ruby开发工程师", "companyName": "瑞卡连锁租车集团", "jobNature": "全职", "positonTypesMap": "None", "totalCount": 0, "positionFirstType": "技术", "adWord": 0, "positionId": 979558, "randomScore": 0, "companyShortName": "瑞致（广州）租车有限公司", "showCount": 54, "haveDeliver": "False", "hrScore": 32, "plus": "否", "positionType": "后端开发", "searchScore": 0.0, "positionAdvantage": "牛人团队氛围好成长快五天七小时交通便利", "adjustScore": 0}, {"orderBy": 24, "leaderName": "暂没有填写", "calcScore": "False", "companySize": "15-50人", "deliverCount": 0, "countAdjusted": "False", "flowScore": 84, "workYear": "不限", "education": "学历不限", "financeStage": "初创型(未融资)", "pvScore": 12.21066196711653, "city": "广州", "companyLogo": "image2/M00/02/E3/CgqLKVXs2GSALnCHAAAcd5_TgNI705.png", "createTimeSort": 1452658922000, "companyId": 62288, "industryField": "移动互联网 · 企业服务", "createTime": "2016-01-13 12:22:02", "score": 926, "imstate": "disabled", "relScore": 765, "formatCreateTime": "2016-01-13", "showOrder": 0, "salary": "3k-5k", "positionName": "Ruby开发实习生", "companyName": "Beansmile", "jobNature": "实习", "positonTypesMap": "None", "totalCount": 0, "positionFirstType": "技术", "adWord": 0, "positionId": 1204603, "randomScore": 0, "companyShortName": "广州乐豆信息科技有限公司", "showCount": 43, "haveDeliver": "False", "hrScore": 53, "plus": "否", "positionType": "后端开发", "searchScore": 0.0, "positionAdvantage": "良好的学习氛围，接触前沿技术的机会", "adjustScore": 0}, {"orderBy": 50, "leaderName": "何驰", "calcScore": "False", "companySize": "15-50人", "deliverCount": 0, "countAdjusted": "False", "flowScore": 186, "workYear": "3-5年", "education": "学历不限", "financeStage": "初创型(不需要融资)", "pvScore": 6.2676827439182725, "city": "广州", "companyLogo": "image1/M00/00/19/CgYXBlTUWFSAfwYKAABVPZmQgqQ393.png", "createTimeSort": 1453685410000, "companyId": 13023, "industryField": "移动互联网 · 数据服务", "createTime": "2016-01-25 09:30:10", "score": 925, "imstate": "disabled", "relScore": 624, "formatCreateTime": "3天前发布", "showOrder": 1432609295224, "salary": "15k-20k", "positionName": "高级Ruby/Rails开发工程师", "companyName": "艾道", "jobNature": "全职", "positonTypesMap": "None", "totalCount": 0, "positionFirstType": "技术", "adWord": 0, "positionId": 553726, "randomScore": 0, "companyShortName": "广州艾道信息咨询有限公司", "showCount": 46, "haveDeliver": "False", "hrScore": 65, "plus": "否", "positionType": "后端开发", "searchScore": 0.0, "positionAdvantage": "SAAS项目，敏捷团队", "adjustScore": 0}, {"orderBy": 8, "leaderName": "张翼", "calcScore": "False", "companySize": "少于15人", "deliverCount": 0, "countAdjusted": "False", "flowScore": 30, "workYear": "不限", "education": "学历不限", "financeStage": "初创型(天使轮)", "pvScore": 15.361342580788715, "city": "广州", "companyLogo": "image1/M00/10/C0/Cgo8PFT_qbqANFUoAACF3teOsL8182.jpg", "createTimeSort": 1449897176000, "companyId": 55642, "industryField": "移动互联网 · O2O", "createTime": "2015-12-12 13:12:56", "score": 879, "imstate": "disabled", "relScore": 800, "formatCreateTime": "2015-12-12", "showOrder": 1431236235604, "salary": "10k-20k", "positionName": "高级ruby工程师", "companyName": "晒尔科技", "jobNature": "全职", "positonTypesMap": "None", "totalCount": 0, "positionFirstType": "技术", "adWord": 0, "positionId": 523984, "randomScore": 0, "companyShortName": "深圳晒尔科技有限公司", "showCount": 35, "haveDeliver": "False", "hrScore": 41, "plus": "否", "positionType": "后端开发", "searchScore": 0.0, "positionAdvantage": "用GEEK精神，创造利他价值！", "adjustScore": 0}, {"orderBy": 50, "leaderName": "何驰", "calcScore": "False", "companySize": "15-50人", "deliverCount": 0, "countAdjusted": "False", "flowScore": 197, "workYear": "1-3年", "education": "学历不限", "financeStage": "初创型(不需要融资)", "pvScore": 5.586414856666937, "city": "广州", "companyLogo": "image1/M00/00/19/CgYXBlTUWFSAfwYKAABVPZmQgqQ393.png", "createTimeSort": 1453685404000, "companyId": 13023, "industryField": "移动互联网 · 数据服务", "createTime": "2016-01-25 09:30:04", "score": 870, "imstate": "disabled", "relScore": 558, "formatCreateTime": "3天前发布", "showOrder": 1432609300865, "salary": "5k-8k", "positionName": "Rails &amp; Ruby 开发工程师", "companyName": "艾道", "jobNature": "全职", "positonTypesMap": "None", "totalCount": 0, "positionFirstType": "技术", "adWord": 0, "positionId": 278196, "randomScore": 0, "companyShortName": "广州艾道信息咨询有限公司", "showCount": 41, "haveDeliver": "False", "hrScore": 65, "plus": "否", "positionType": "后端开发", "searchScore": 0.0, "positionAdvantage": "SAAS项目，白金五星办公，职业发展前景好", "adjustScore": 0}, {"orderBy": 15, "leaderName": "金鑫", "calcScore": "False", "companySize": "50-150人", "deliverCount": 0, "countAdjusted": "False", "flowScore": 0, "workYear": "1年以下", "education": "学历不限", "financeStage": "成长型(A轮)", "pvScore": 22.032195145592343, "city": "广州", "companyLogo": "image1/M00/00/66/CgYXBlTUXWeAadZWAABA0vEUhyc609.jpg", "createTimeSort": 1450162407000, "companyId": 41411, "industryField": "移动互联网", "createTime": "2015-12-15 14:53:27", "score": 769, "imstate": "disabled", "relScore": 744, "formatCreateTime": "2015-12-15", "showOrder": 0, "salary": "10k-15k", "positionName": "初级Ruby开发工程师", "companyName": "持创", "jobNature": "全职", "positonTypesMap": "None", "totalCount": 0, "positionFirstType": "技术", "adWord": 0, "positionId": 1345977, "randomScore": 0, "companyShortName": "北京持创信息技术有限公司", "showCount": 38, "haveDeliver": "False", "hrScore": 10, "plus": "否", "positionType": "后端开发", "searchScore": 0.0, "positionAdvantage": "五险一金、双休日、年休假", "adjustScore": 0}, {"orderBy": 50, "leaderName": "何驰", "calcScore": "False", "companySize": "15-50人", "deliverCount": 0, "countAdjusted": "False", "flowScore": 151, "workYear": "不限", "education": "学历不限", "financeStage": "初创型(不需要融资)", "pvScore": 8.311495274553248, "city": "广州", "companyLogo": "image1/M00/00/19/CgYXBlTUWFSAfwYKAABVPZmQgqQ393.png", "createTimeSort": 1453685413000, "companyId": 13023, "industryField": "移动互联网 · 数据服务", "createTime": "2016-01-25 09:30:13", "score": 406, "imstate": "disabled", "relScore": 140, "formatCreateTime": "3天前发布", "showOrder": 1432609299084, "salary": "3k-4k", "positionName": "Ruby&amp;Rails 开发实习生", "companyName": "艾道", "jobNature": "实习", "positonTypesMap": "None", "totalCount": 0, "positionFirstType": "技术", "adWord": 0, "positionId": 278206, "randomScore": 0, "companyShortName": "广州艾道信息咨询有限公司", "showCount": 61, "haveDeliver": "False", "hrScore": 65, "plus": "否", "positionType": "后端开发", "searchScore": 0.0, "positionAdvantage": "SAAS项目，白金五星办公，职业发展前景好", "adjustScore": 0}]
