[{"orderBy": 50, "leaderName": "暂没有填写", "calcScore": "False", "companySize": "15-50人", "deliverCount": 0, "countAdjusted": "False", "flowScore": 120, "workYear": "3-5年", "education": "大专", "financeStage": "初创型(天使轮)", "pvScore": 5.265990451863293, "city": "武汉", "companyLogo": "image2/M00/08/34/CgpzWlYCEOWAT2FXAAANp38EMVU550.jpg", "createTimeSort": 1453684092000, "companyId": 95178, "industryField": "移动互联网", "score": 1191, "imstate": "disabled", "relScore": 1000, "formatCreateTime": "3天前发布", "showOrder": 0, "salary": "10k-20k", "positionName": "SQLServer", "companyName": "卡斯姆", "jobNature": "全职", "positonTypesMap": "None", "totalCount": 0, "positionFirstType": "技术", "adWord": 0, "createTime": "2016-01-25 09:08:12", "positionId": 1420731, "randomScore": 0, "companyShortName": "武汉卡斯姆科技发展有限公司", "showCount": 28, "haveDeliver": "False", "hrScore": 22, "plus": "否", "positionType": "dba", "searchScore": 0.0, "positionAdvantage": "竞争力的待遇，五险一金 美女 福利", "adjustScore": 0}]
